docs/make.py
sfapp/__init__.py
sfapp/__main__.py
sfapp/py.typed
sfapp/showwarning.py
sfapp/classes/importdict.py
sfapp/classes/module.py
sfapp/classes/moduleimport.py
sfapp/classes/singlefileappbuilder.py
sfapp/classes/sourcefile.py
sfapp-1.0.2.dist-info/licenses/LICENSE
tests/test_base.py
sfapp-1.0.2.dist-info/METADATA
sfapp-1.0.2.dist-info/WHEEL
sfapp-1.0.2.dist-info/entry_points.txt
sfapp-1.0.2.dist-info/top_level.txt
sfapp-1.0.2.dist-info/RECORD
