Metadata-Version: 2.4
Name: sfapp
Version: 1.0.2
Summary: SFApp is a module to bundle a Python package into a single file Python script.
Author-email: Etienne_MR <etienne@etiennemr.fr>
License-Expression: MIT
Project-URL: Homepage, https://github.com/EtienneMR/sfapp
Classifier: Programming Language :: Python :: 3
Classifier: Operating System :: OS Independent
Requires-Python: >=3.8
License-File: LICENSE
Dynamic: license-file
